football_data_api/__init__.py
football_data_api/data_fetchers.py
football_data_api-0.0.6.dist-info/METADATA
football_data_api-0.0.6.dist-info/RECORD
football_data_api-0.0.6.dist-info/WHEEL
football_data_api-0.0.6.dist-info/top_level.txt
tests/__init__.py
tests/test_football_data_api.py
