Metadata-Version: 2.1
Name: football_data_api
Version: 0.0.6
Summary: Python interface for the football-data.org api from Daniel.
Home-page: https://github.com/miquel-vv/football_data_api
Author: Miquel Vande Velde
Author-email: miquel.vandevelde@gmail.com
License: UNKNOWN
Keywords: football,data,football-data.org
Platform: UNKNOWN
Classifier: Programming Language :: Python :: 3
Classifier: License :: OSI Approved :: MIT License
Classifier: Operating System :: OS Independent
